lmnr_flow/__init__.py
lmnr_flow/context.py
lmnr_flow/flow.py
lmnr_flow/state.py
lmnr_flow-0.1.5.dist-info/METADATA
lmnr_flow-0.1.5.dist-info/WHEEL
lmnr_flow-0.1.5.dist-info/licenses/LICENSE
lmnr_flow-0.1.5.dist-info/RECORD
