Metadata-Version: 2.4
Name: lmnr-flow
Version: 0.1.5
Summary: Lightweight task engine for building AI agents
Project-URL: Homepage, https://github.com/lmnr-ai/flow
Project-URL: Bug Tracker, https://github.com/lmnr-ai/flow/issues
License:                                  Apache License
License-File: LICENSE
Requires-Python: >=3.10
Requires-Dist: lmnr>=0.4.49
